libres/.gitignore
libres/__init__.py
libres/py.typed
libres/context/__init__.py
libres/context/core.py
libres/context/exposure.py
libres/context/registry.py
libres/context/session.py
libres/context/settings.py
libres/db/__init__.py
libres/db/queries.py
libres/db/scheduler.py
libres/db/models/__init__.py
libres/db/models/allocation.py
libres/db/models/base.py
libres/db/models/blocker.py
libres/db/models/other.py
libres/db/models/reservation.py
libres/db/models/reserved_slot.py
libres/db/models/timespan.py
libres/db/models/timestamp.py
libres/db/models/types/__init__.py
libres/db/models/types/json_type.py
libres/db/models/types/utcdatetime.py
libres/db/models/types/uuid_type.py
libres/modules/__init__.py
libres/modules/errors.py
libres/modules/events.py
libres/modules/rasterizer.py
libres/modules/utils.py
libres-0.10.1.dist-info/licenses/LICENSE
libres-0.10.1.dist-info/METADATA
libres-0.10.1.dist-info/WHEEL
libres-0.10.1.dist-info/top_level.txt
libres-0.10.1.dist-info/RECORD
