Metadata-Version: 2.4
Name: libres
Version: 0.10.1
Summary: A library to reserve things
Home-page: http://github.com/seantis/libres/
Author: Denis Krienbühl
Author-email: denis@href.ch
Maintainer: Seantis GmbH
Maintainer-email: info@seantis.ch
License: BSD
Classifier: Development Status :: 4 - Beta
Classifier: Intended Audience :: Developers
Classifier: License :: OSI Approved :: BSD License
Classifier: Operating System :: OS Independent
Classifier: Programming Language :: Python
Classifier: Programming Language :: Python :: 3
Classifier: Programming Language :: Python :: 3.9
Classifier: Programming Language :: Python :: 3.10
Classifier: Programming Language :: Python :: 3.11
Classifier: Programming Language :: Python :: 3.12
Classifier: Programming Language :: Python :: 3.13
Classifier: Topic :: Software Development :: Libraries :: Python Modules
Requires-Python: >=3.9
License-File: LICENSE
Requires-Dist: python-dateutil
Requires-Dist: psycopg2-binary
Requires-Dist: pytz
Requires-Dist: sedate>=1.0.0
Requires-Dist: SQLAlchemy<2,>=0.9
Provides-Extra: dev
Requires-Dist: bandit[toml]; extra == "dev"
Requires-Dist: bump-my-version; extra == "dev"
Requires-Dist: flake8; extra == "dev"
Requires-Dist: flake8-type-checking; extra == "dev"
Requires-Dist: pre-commit; extra == "dev"
Requires-Dist: pre-commit-uv; extra == "dev"
Requires-Dist: ruff; extra == "dev"
Requires-Dist: uv; extra == "dev"
Requires-Dist: tox; extra == "dev"
Requires-Dist: tox-uv; extra == "dev"
Provides-Extra: test
Requires-Dist: jsonpickle; extra == "test"
Requires-Dist: pytest; extra == "test"
Requires-Dist: pytest-codecov[git]; extra == "test"
Requires-Dist: testing.postgresql; extra == "test"
Provides-Extra: mypy
Requires-Dist: mypy; extra == "mypy"
Requires-Dist: sqlalchemy-stubs; extra == "mypy"
Requires-Dist: types-psycopg2; extra == "mypy"
Requires-Dist: types-python-dateutil; extra == "mypy"
Requires-Dist: types-pytz; extra == "mypy"
Requires-Dist: typing-extensions; extra == "mypy"
Dynamic: license-file
